odoo/addons/contract/README.rst
odoo/addons/contract/__init__.py
odoo/addons/contract/__manifest__.py
odoo/addons/contract/data/contract_cron.xml
odoo/addons/contract/data/mail_template.xml
odoo/addons/contract/i18n/am.po
odoo/addons/contract/i18n/ar.po
odoo/addons/contract/i18n/bg.po
odoo/addons/contract/i18n/bs.po
odoo/addons/contract/i18n/ca.po
odoo/addons/contract/i18n/cs.po
odoo/addons/contract/i18n/da.po
odoo/addons/contract/i18n/de.po
odoo/addons/contract/i18n/el_GR.po
odoo/addons/contract/i18n/en_GB.po
odoo/addons/contract/i18n/es.po
odoo/addons/contract/i18n/es_AR.po
odoo/addons/contract/i18n/es_CO.po
odoo/addons/contract/i18n/es_CR.po
odoo/addons/contract/i18n/es_DO.po
odoo/addons/contract/i18n/es_EC.po
odoo/addons/contract/i18n/es_ES.po
odoo/addons/contract/i18n/es_MX.po
odoo/addons/contract/i18n/es_PY.po
odoo/addons/contract/i18n/es_VE.po
odoo/addons/contract/i18n/et.po
odoo/addons/contract/i18n/eu.po
odoo/addons/contract/i18n/fa.po
odoo/addons/contract/i18n/fi.po
odoo/addons/contract/i18n/fr.po
odoo/addons/contract/i18n/fr_CA.po
odoo/addons/contract/i18n/fr_CH.po
odoo/addons/contract/i18n/gl.po
odoo/addons/contract/i18n/gl_ES.po
odoo/addons/contract/i18n/he.po
odoo/addons/contract/i18n/hi_IN.po
odoo/addons/contract/i18n/hr.po
odoo/addons/contract/i18n/hr_HR.po
odoo/addons/contract/i18n/hu.po
odoo/addons/contract/i18n/id.po
odoo/addons/contract/i18n/it.po
odoo/addons/contract/i18n/ja.po
odoo/addons/contract/i18n/ko.po
odoo/addons/contract/i18n/lt.po
odoo/addons/contract/i18n/lt_LT.po
odoo/addons/contract/i18n/lv.po
odoo/addons/contract/i18n/mk.po
odoo/addons/contract/i18n/mn.po
odoo/addons/contract/i18n/nb.po
odoo/addons/contract/i18n/nb_NO.po
odoo/addons/contract/i18n/nl.po
odoo/addons/contract/i18n/nl_BE.po
odoo/addons/contract/i18n/nl_NL.po
odoo/addons/contract/i18n/pl.po
odoo/addons/contract/i18n/pt.po
odoo/addons/contract/i18n/pt_BR.po
odoo/addons/contract/i18n/pt_PT.po
odoo11_addon_contract-11.0.2.1.0.dist-info/DESCRIPTION.rst
odoo11_addon_contract-11.0.2.1.0.dist-info/METADATA
odoo11_addon_contract-11.0.2.1.0.dist-info/RECORD
odoo11_addon_contract-11.0.2.1.0.dist-info/WHEEL
odoo11_addon_contract-11.0.2.1.0.dist-info/metadata.json
odoo11_addon_contract-11.0.2.1.0.dist-info/top_level.txt
